README.rst
setup.py
./agglo_cc/__init__.py
./agglo_cc/exceptions.py
./agglo_cc/_private/__init__.py
./agglo_cc/_private/cli_io_parser.py
./agglo_cc/core/__init__.py
./agglo_cc/core/cli_client.py
./agglo_cc/core/cli_io_handler.py
./agglo_cc/core/cli_io_types.py
./agglo_cc/core/cli_serializable.py
./agglo_cc/core/command_results.py
./agglo_cc/core/menu.py
./agglo_cc/core/menu_navigator.py
./agglo_cc/core/menu_path.py
./agglo_cc/utils/__init__.py
./agglo_cc/utils/script_recorder.py
./agglo_cc/xsl/generate_cli_client.sh
./agglo_cc/xsl/menu_generator.xsl
agglo_cc.egg-info/PKG-INFO
agglo_cc.egg-info/SOURCES.txt
agglo_cc.egg-info/dependency_links.txt
agglo_cc.egg-info/requires.txt
agglo_cc.egg-info/top_level.txt